keradb/__init__.py
keradb/client.py
keradb/ffi.py
keradb/results.py
keradb/vector.py
keradb-0.1.0.dist-info/METADATA
keradb-0.1.0.dist-info/WHEEL
keradb-0.1.0.dist-info/top_level.txt
keradb-0.1.0.dist-info/RECORD
