Metadata-Version: 2.4
Name: keradb
Version: 0.1.0
Summary: MongoDB-compatible Python client for KeraDB - a lightweight embedded NoSQL database with vector search
Author: KeraDB Team
License: MIT
Project-URL: Homepage, https://github.com/keradb/keradb
Project-URL: Documentation, https://keradb.github.io
Project-URL: Repository, https://github.com/keradb/keradb
Project-URL: Issues, https://github.com/keradb/keradb/issues
Keywords: database,nosql,embedded,document,storage,vector-search,mongodb-compatible,keradb
Classifier: Development Status :: 4 - Beta
Classifier: Intended Audience :: Developers
Classifier: License :: OSI Approved :: MIT License
Classifier: Programming Language :: Python :: 3
Classifier: Programming Language :: Python :: 3.8
Classifier: Programming Language :: Python :: 3.9
Classifier: Programming Language :: Python :: 3.10
Classifier: Programming Language :: Python :: 3.11
Classifier: Programming Language :: Python :: 3.12
Classifier: Topic :: Database
Classifier: Topic :: Software Development :: Libraries :: Python Modules
Requires-Python: >=3.8
Provides-Extra: dev
Requires-Dist: pytest>=7.0.0; extra == "dev"
Requires-Dist: pytest-benchmark>=4.0.0; extra == "dev"
Requires-Dist: numpy>=1.20.0; extra == "dev"
Provides-Extra: benchmark
Requires-Dist: pytest-benchmark>=4.0.0; extra == "benchmark"
Requires-Dist: numpy>=1.20.0; extra == "benchmark"
